CHANGELOG.txt
LICENSE.txt
MANIFEST.in
README.txt
setup.py
skyway/__init__.py
skyway.egg-info/PKG-INFO
skyway.egg-info/SOURCES.txt
skyway.egg-info/dependency_links.txt
skyway.egg-info/top_level.txt