Metadata-Version: 1.1
Name: skyway
Version: 0.0.2
Summary: Use Your Imagination
Home-page: UNKNOWN
Author: Yigido
Author-email: yigitgulay11@outlook.com
License: MIT
Keywords: skyway
Platform: UNKNOWN
Classifier: Development Status :: 5 - Production/Stable
Classifier: Intended Audience :: Education
Classifier: Operating System :: Microsoft :: Windows :: Windows 10
Classifier: License :: OSI Approved :: MIT License
Classifier: Programming Language :: Python :: 3
